wavemix/SemSegment.py
wavemix/__init__.py
wavemix/classification.py
wavemix/sisr.py
wavemix-0.2.4.dist-info/LICENSE
wavemix-0.2.4.dist-info/METADATA
wavemix-0.2.4.dist-info/WHEEL
wavemix-0.2.4.dist-info/top_level.txt
wavemix-0.2.4.dist-info/RECORD
